discord/ext/ipc/__init__.py
discord/ext/ipc/client.py
discord/ext/ipc/errors.py
discord/ext/ipc/objects.py
discord/ext/ipc/server.py
discord_ipc-0.1.0.dist-info/LICENSE
discord_ipc-0.1.0.dist-info/METADATA
discord_ipc-0.1.0.dist-info/WHEEL
discord_ipc-0.1.0.dist-info/top_level.txt
discord_ipc-0.1.0.dist-info/RECORD
