Metadata-Version: 2.1
Name: discord-ipc
Version: 0.1.0
Summary: Discord IPC
Home-page: https://github.com/benforster/discord-ext-ipc
Author: benforster
Author-email: benfo1942@gmail.com
Classifier: Programming Language :: Python :: 3.9
Classifier: License :: OSI Approved :: MIT License
Classifier: Operating System :: OS Independent
License-File: LICENSE
Requires-Dist: websockets
Provides-Extra: speed
Requires-Dist: orjson ; extra == 'speed'
